analytics/__init__.py
analytics/filters.py
core/__init__.py
core/cache.py
core/parser.py
core/sheets_client.py
innosched/__init__.py
innosched/cache.py
innosched/sheets_client.py
models/__init__.py
models/schedule.py
innoscheduleapi-0.1.1.dist-info/METADATA
innoscheduleapi-0.1.1.dist-info/WHEEL
innoscheduleapi-0.1.1.dist-info/top_level.txt
innoscheduleapi-0.1.1.dist-info/RECORD
