Metadata-Version: 2.4
Name: innoscheduleapi
Version: 0.1.1
Summary: Parser and analytics library for Innopolis University schedule
Author: Dreaght
Requires-Python: >=3.10
Requires-Dist: google-api-python-client
Requires-Dist: google-auth
